sysdreader/__init__.py
sysdreader/journal_reader.py
sysdreader-0.0.3.dist-info/METADATA
sysdreader-0.0.3.dist-info/RECORD
sysdreader-0.0.3.dist-info/WHEEL
sysdreader-0.0.3.dist-info/top_level.txt
