Metadata-Version: 2.1
Name: sysdreader
Version: 0.0.3
Summary: A small journalctl reader
Home-page: UNKNOWN
Author: Ömer Gök
Author-email: omergok@outlook.com
License: UNKNOWN
Platform: UNKNOWN
Classifier: Programming Language :: Python :: 3
Classifier: Operating System :: OS Independent
Requires-Dist: python-systemd
